artifactable/__init__.py
artifactable/__main__.py
artifactable/client.py
artifactable/commands.py
artifactable/config.py
artifactable/loggers.py
artifactable-0.2.1.dist-info/LICENSE
artifactable-0.2.1.dist-info/METADATA
artifactable-0.2.1.dist-info/WHEEL
artifactable-0.2.1.dist-info/entry_points.txt
artifactable-0.2.1.dist-info/top_level.txt
artifactable-0.2.1.dist-info/RECORD
