Metadata-Version: 2.1
Name: artifactable
Version: 0.2.1
Summary: Command line interface for working with artifactable services.
Home-page: https://github.com/artifactable-repos/cli
Author: Tom Waterman
Author-email: tjwaterman99@gmail.com
License: UNKNOWN
Platform: UNKNOWN
License-File: LICENSE
Requires-Dist: requests (<2.24.0)
Requires-Dist: click (==8.0.1)
Requires-Dist: PyYAML (==5.4.1)
